README.md
setup.py
mo_fabric/__init__.py
mo_fabric.egg-info/PKG-INFO
mo_fabric.egg-info/SOURCES.txt
mo_fabric.egg-info/dependency_links.txt
mo_fabric.egg-info/not-zip-safe
mo_fabric.egg-info/requires.txt
mo_fabric.egg-info/top_level.txt