Metadata-Version: 2.1
Name: mo-fabric
Version: 2.28.18331
Summary: Thin facade over fabric
Home-page: https://github.com/klahnakoski/mo-fabric
Author: Kyle Lahnakoski
Author-email: kyle@lahnakoski.com
License: MPL 2.0
Platform: UNKNOWN
Classifier: Development Status :: 4 - Beta
Classifier: Topic :: Software Development :: Libraries
Classifier: Topic :: Software Development :: Libraries :: Python Modules
Classifier: License :: OSI Approved :: Mozilla Public License 2.0 (MPL 2.0)
